markdownusm/__init__.py
markdownusm/cli.py
markdownusm/parser.py
markdownusm/tests/test_integration.py
markdownusm/tests/test_parser.py
markdownusm/tests/test_usm.py
markdownusm/tests/test_xml.py
markdownusm/usm.py
markdownusm/xml.py
markdownusm-0.2.0.post2.dist-info/entry_points.txt
markdownusm-0.2.0.post2.dist-info/LICENSE
markdownusm-0.2.0.post2.dist-info/WHEEL
markdownusm-0.2.0.post2.dist-info/METADATA
markdownusm-0.2.0.post2.dist-info/RECORD
