Metadata-Version: 2.1
Name: markdownusm
Version: 0.2.0.post2
Summary: MarkdownUSM is the best way to draw a beautiful user story mapping diagram from simple markdown file.
Home-page: https://github.com/kbyky
License: MIT
Author: kbyky
Author-email: kbyky36@gmail.com
Requires-Python: >=3.9,<4.0
Classifier: License :: OSI Approved :: MIT License
Classifier: Programming Language :: Python :: 3
Classifier: Programming Language :: Python :: 3.9
Requires-Dist: Jinja2 (>=3.0.1,<4.0.0)
Requires-Dist: pydantic (>=1.8.2,<2.0.0)
Project-URL: Repository, https://github.com/kbyky/markdownusm
